[
  {
    "id": 1,
    "title": "Zoo Arcadia",
    "description": "Application web destinée aux visiteurs et aux employés du zoo avec une interface administrateur.",
    "image": "assets/images/ProjetArcadia.png",
    "technologies": ["Symfony", "SQL & NoSQL", "API REST"],
    "url": "https://th1bz-arcadia.alwaysdata.net/",
    "status": "active",
    "category": "application"
  },
  {
    "id": 2,
    "title": "CheckIt",
    "description": "Application web pour créer et gérer des listes de tâches.",
    "image": "assets/images/ProjetCheckIt.png",
    "technologies": ["PHP", "MySQL", "Bootstrap"],
    "url": "#",
    "status": "disabled",
    "category": "application"
  },
  {
    "id": 3,
    "title": "Calculatrice",
    "description": "Développement d'une calculatrice simple avec Vite.js, React et Tailwind CSS.",
    "image": "assets/images/HomeCalculatrice.png",
    "technologies": ["Vite.js", "React", "Tailwind CSS"],
    "url": "https://th1bz.github.io/Calculatrice-React-et-Tailwindcss/",
    "status": "active",
    "category": "application"
  },
  {
    "id": 4,
    "title": "Template Site Vitrine",
    "description": "Développement d'un template de site vitrine personnalisable simple et responsive.",
    "image": "assets/images/Screen_Template-V1.png",
    "technologies": ["HTML5", "CSS3", "JavaScript"],
    "url": "https://th1bz.github.io/Template-V1/",
    "status": "active",
    "category": "template"
  },
  {
    "id": 5,
    "title": "Template Site Vitrine 2",
    "description": "Développement d'un template de site vitrine personnalisable simple et responsive.",
    "image": "assets/images/Screen_Template-V1.png",
    "technologies": ["HTML5", "CSS3", "JavaScript"],
    "url": "https://th1bz.github.io/Template-V1/",
    "status": "active",
    "category": "template"
  }
]
